dolang/__init__.py
dolang/codegen.py
dolang/factory.py
dolang/function_compiler.py
dolang/grammar.lark
dolang/grammar.py
dolang/language.py
dolang/latex.py
dolang/objects.py
dolang/pattern.py
dolang/symbolic.py
dolang/symbolic_old.py
dolang/symbols.py
dolang/tests/consumption_savings.dot
dolang/tests/portfolio.dot
dolang/tests/rbc.dot
dolang/tests/syntax_errors.yaml
dolang/tests/test_compiler.py
dolang/tests/test_latex.py
dolang/tests/test_patterns.py
dolang/tests/test_symbolic.py
dolang/tests/test_symbols.py
dolang/tests/test_syntax_errors.py
dolang/tests/test_yaml_tools.py
dolang/triangular_solver.py
dolang/vectorize.py
dolang/version.py
dolang/yaml_tools.py
dolang-0.0.21.dist-info/LICENSE
dolang-0.0.21.dist-info/METADATA
dolang-0.0.21.dist-info/WHEEL
dolang-0.0.21.dist-info/RECORD
